Workbook

Sheet Start Here
B2: Capacity, Scheduling & Engagement -- the unabridged variable workbook
B3: Every variable in the 8.13 inventory, placed under the three arenas of the vendor one-pager, in the same plain language. Built to be edited as we talk through each scenario, and to be the source the future-state maps are drawn from.
B6: What is in here
B7: Master List | C7: One row per variable — 93 of them, the full inventory with nothing dropped. This is the sheet we edit together. Six rows are highlighted: the incentives row, which the vendor questionnaire has asked about since 21 Aug but which carried no ID, and five variables the 13 Aug session confirmed as real but never had a row drafted. All six need MVP, gating and posture confirmed.
B8: Roles | C8: Who each role is, and the colour it carries on the current-state flow maps. Use these names in the two owner columns so the future-state maps stay consistent.
B9: Lists | C9: The permitted values behind the drop-downs. Change a value here and the drop-down changes everywhere.
B11: How to read a row
B12: Arena (8.19 workbook) | C12: Straight from the Module column of the 19 Aug workbook. That column is authoritative — change it there, not here.
B13: Also touches | C13: The other arenas the variable shows up in. Plenty are shared — that is expected, not a problem to resolve.
B14: One-pager group | C14: The ten group headings from the vendor one-pager. Part B of the questionnaire scores exactly these groups.
B15: Placement check | C15: Whether the workbook and the one-pager agree on where this belongs. They disagree on a number of rows — neither is wrong, the workbook is the internal model and the one-pager is the vendor view, but a vendor answering under one heading while we score under another gives a false coverage read. The disagreements are surfaced here rather than resolved.
B16: In plain terms | C16: Written for a reader with no home-health background. If a sentence needs clinical knowledge to parse, it needs rewriting.
B17: Who does the work today | C17: The role that physically performs the task. Shared ownership is fine — 'DCS and Scheduler' is a real answer.
B18: Who reads it and decides today | C18: The role that looks at the result and acts. Often a different person from the one who does the work, and sometimes the honest answer is nobody — those rows are marked '— no one today' and they are the interesting ones.
B19: Where the information lives today | C19: The system, screen or note it sits in. Shaded by how sure we are — see the confidence key below.
B20: Future state -- the tool's role | C20: Automate (the tool does it), Assist (the tool proposes, a person confirms), Surface (the tool shows, a person decides), Stays manual (unchanged).
B21: Future state -- who decides | C21: For Assist and Surface rows, the person who confirms or acts. For Automate rows, who owns the exception when automation cannot resolve it.
B22: Trigger / how often | C22: What sets the task off and at what rhythm. This is the column the future-state maps are built from — a map is a sequence of triggers.
B23: Confidence key -- where to jump in first | C23: Stable = record it once and it holds. Drifts = it goes stale unless somebody keeps asking, so it needs a standing engagement mechanism, not a field captured at start of care. Live/computed = recalculated, no decay problem. This is the contact = the row is the outbound work itself.
... B26: Low | C26: Either it lives in a person's head, or it does not exist anywhere today. Start here -- these rows are the real work.
B28: Where the sheet stands -- live counts, these update as you edit
B29: Measure | C29: What it tells us | D29: Count
B30: Rows in total | C30: 87 variables from the 19 Aug inventory, plus 1 flagged gap. Nothing dropped. | D30: =COUNTA('Master List'!$A$2:$A$94)
B31: Capacity Management | C31: Rows the workbook assigns to capacity. | D31: =COUNTIF('Master List'!$B$2:$B$94,"Capacity Management")
B32: Scheduling Engine | C32: Rows the workbook assigns to scheduling. | D32: =COUNTIF('Master List'!$B$2:$B$94,"Scheduling Engine")
B33: Engagement | C33: Rows the workbook assigns to engagement. | D33: =COUNTIF('Master List'!$B$2:$B$94,"Engagement")
B34: Shared across arenas | C34: Rows that also show up somewhere else — the seams. | D34: =COUNTIF('Master List'!$C$2:$C$94,"?*")
B35: Placement differs from the one-pager | C35: DECISION NEEDED. The workbook and the vendor page disagree on where these belong. | D35: =COUNTIF('Master List'!$E$2:$E$94,"Differs*")
B36: Low confidence on source | C36: START HERE. We do not know where this lives. | D36: =COUNTIF('Master List'!$K$2:$K$94,"Low")
B37: Medium confidence on source | C37: Right system, wrong-or-unknown screen. | D37: =COUNTIF('Master List'!$K$2:$K$94,"Medium")
B38: High confidence on source | C38: Settled. | D38: =COUNTIF('Master List'!$K$2:$K$94,"High")
B39: Nobody decides today | C39: No role reads the result. The clearest opportunities on the sheet. | D39: =COUNTIF('Master List'!$I$2:$I$94,"— no one*")
B40: Future state: Automate | C40: The tool does it end to end. | D40: =COUNTIF('Master List'!$L$2:$L$94,"Automate")
B41: Future state: Assist | C41: The tool proposes, a person confirms. | D41: =COUNTIF('Master List'!$L$2:$L$94,"Assist")
B42: Future state: Surface | C42: The tool shows, a person decides. | D42: =COUNTIF('Master List'!$L$2:$L$94,"Surface")
B43: Drifts — needs re-contact | C43: THE ENGAGEMENT LOAD. These go stale unless somebody keeps asking. | D43: =COUNTIF('Master List'!$O$2:$O$94,"Drifts*")
B44: ...and sitting outside Engagement | C44: Capacity and scheduling rows that still need an engagement mechanism under them. | D44: =COUNTIFS('Master List'!$O$2:$O$94,"Drifts*",'Master List'!$B$2:$B$94,"<>Engagement")
B45: ...caught in the day-before round | C45: The single recurring contact point the process already has. Today it is manual, every patient, every day. | D45: =COUNTIF('Master List'!$P$2:$P$94,"Day before*")
B46: ...caught in the weekly build | C46: The clinician's own weekly planning pass. | D46: =COUNTIF('Master List'!$P$2:$P$94,"Weekly*")
B47: ...with no re-check at all | C47: Drifts, and nothing catches it. Silent staleness. | D47: =COUNTIFS('Master List'!$O$2:$O$94,"Drifts*",'Master List'!$P$2:$P$94,"Not re-checked today")
B48: High adoption sensitivity | C48: Rows where the change lands on clinicians. Design these with them. | D48: =COUNTIF('Master List'!$S$2:$S$94,"High")
B49: Day-one must-haves | C49: MVP = Yes. | D49: =COUNTIF('Master List'!$Q$2:$Q$94,"Yes")
B50: Knockout requirements | C50: Gating = Y. A product that cannot do these should not advance. | D50: =COUNTIF('Master List'!$R$2:$R$94,"Y")
B52: A worked row, so the expected format is obvious
B53: ID | C53: C-03
B54: Arena (8.19 workbook) | C54: Capacity Management
B55: Also touches | C55: Scheduling
B56: One-pager group | C56: Availability & reach
B57: Placement check | C57: Aligned
B58: In plain terms | C58: Which zip codes each clinician covers. Territories were drawn on thin data and have stayed static, so capacity drifts away from demand quietly.
B59: Who does the work today | C59: DCS and Scheduler — assign and adjust
B60: Who reads it and decides today | C60: Branch Leadership (ED) with DCS — at the joint review when capacity tightens
B61: Where it lives today | C61: HCHB holds the assignment where it has been entered; the working version is often the scheduler's own reference.
B62: Confidence | C62: Medium
B63: Future state | C63: Assist — the tool proposes territory changes against a live census heat-map
B64: Future state -- who decides | C64: Branch Leadership (ED) with DCS
... B66: Adoption sensitivity | C66: High
B68: Editing conventions
B69: Everything is editable | C69: Nothing is locked. The drop-down columns accept typed values too, so a shared answer like 'DCS and Scheduler' is always allowed.
B70: Say 'no one' when it is true | C70: If nobody reads a report today, write '— no one today'. Those rows are counted above and they are where the value is.
B71: Keep IDs untouched | C71: The ID column is the join key back to the 8.13 workbook. Never renumber it.
B72: This does not overwrite the workbook | C72: The 8.13 workbook stays authoritative for the variables themselves. This sheet adds the ownership and future-state layer on top.
B74: Sources: variables and IDs from the 8.13 Compassus Capacity & Scheduling Workbook (Variable Inventory + Definitions & Concepts tabs). Plain-language wording follows the vendor one-pager as it stands in the 21 Aug questionnaire Overview tab. Current-state ownership follows the 17-18 Aug flow-mapping facts. Where-it-lives entries are first-pass hypotheses, not findings -- the confidence shading says how much to trust each one.

Sheet Master List
A1: ID | B1: Arena (8.19 workbook) | C1: Also touches | D1: One-pager group | E1: Placement check | F1: Variable (workbook name) | G1: In plain terms | H1: Who does the work today | I1: Who reads it and decides today | J1: Where the information lives today | K1: Confidence | L1: Future state -- the tool's role | M1: Future state -- who decides | N1: Trigger / how often | O1: Stays true on its own? | P1: Re-checked when | Q1: MVP | R1: Gating | S1: Adoption sensitivity | T1: Why this posture / watch-out | U1: Open question for the team | V1: Constraint (8.13) | W1: Automation posture (8.13) | X1: Sourced by (8.13) | Y1: Current state (8.13) | Z1: Source of truth (8.13) | AA1: Measurability (8.13) | AB1: Automation confidence (8.13) | AC1: Rollup key (8.13) | AD1: Weight (8.13) | AE1: Conflict risk (8.13)
A2: SH-01 | B2: Capacity Management | C2: Scheduling | D2: Workforce supply | E2: Aligned | F2: Clinician headcount | G2: How many clinicians the branch actually has, counted by discipline. The base number every capacity answer starts from. | H2: HR / Talent — maintains the record | I2: Branch Leadership (ED) — at staffing and budget reviews | J2: Workday — worker record; mirrored into HCHB | K2: High | L2: Automate | M2: Branch Leadership (ED) — owns the exception when the two systems disagree | N2: Continuous — changes on hire/term | O2: Stable | P2: — | Q2: Yes | R2: Y | S2: Low | T2: A clean roster fact in a system of record. The only risk is Workday and HCHB disagreeing. | U2: Which system wins when Workday and HCHB disagree on who is active? | V2: Structural | W2: Control | X2: Branch | Y2: In-system | Z2: Workday + HCHB | AA2: Quantitative | AB2: High | AC2: SHD-A | AD2: 3 | AE2: N
A3: SH-02 | B3: Capacity Management | C3: Scheduling | D3: Workforce supply | E3: Aligned | F3: Discipline | G3: What licence each person holds — RN, LPN, PT, PTA, OT, COTA, SLP, MSW, aide. Capacity is always counted inside a discipline: an RN shortage cannot be covered by a spare PT. | H3: HR / Talent — maintains the record | I3: — no one reviews this today; it is simply read | J3: Workday — worker record; mirrored into HCHB | K3: High | L3: Automate | M3: — exception only | N3: Continuous — changes on hire/term | O3: Stable | P3: — | Q3: Yes | R3: Y | S3: Low | T3: Hard licensure fact, fully in the data. | U3: Are the discipline codes identical in Workday and HCHB, or do they need mapping? | V3: Structural | W3: Control | X3: Branch | Y3: In-system | Z3: Workday + HCHB | AA3: Quantitative | AB3: High | AC3: SHD-A | AD3: 3 | AE3: N
A4: SH-03 | B4: Capacity Management | C4: Scheduling | D4: Workforce supply | E4: Aligned | F4: Role — assessing vs assistant | G4: Whether a clinician can open and evaluate a case (RN, PT, OT, SLP) or only carry follow-up visits (LPN, PTA, COTA). This is the lever behind offloading routine visits so assessing staff are free for admissions. | H4: — derived from discipline, nobody maintains it separately | I4: Clinical Manager / DCS — when deciding what can be offloaded | J4: Derived from discipline | K4: High | L4: Automate | M4: Clinical Manager — owns offload policy | N4: Continuous — derived | O4: Live / computed | P4: — | Q4: Yes | R4: Y | S4: Medium | T4: Deterministic from discipline. The sensitivity is not the data, it is the change-management of moving work to assistants. | U4: Is the assessing/assistant split written down as policy anywhere, or only understood? | V4: Structural | W4: Control | X4: Branch | Y4: In-system | Z4: Derived | AA4: Quantitative | AB4: High | AC4: SHD-A | AD4: 3 | AE4: N
A5: SH-04 | B5: Capacity Management | D5: Workforce supply | E5: Aligned | F5: FTE and employment type | G5: Full-time, part-time, per-diem or contract — and the fraction of a full week each person is expected to work. Sets the ceiling of what any individual can carry. | H5: HR / Talent — maintains the record | I5: Branch Leadership (ED) — at staffing reviews | J5: Workday — worker record | K5: High | L5: Automate | M5: Branch Leadership (ED) | N5: Continuous — changes on status change | O5: Stable | P5: — | Q5: Yes | R5: Y | S5: Low | T5: Clean employment attribute. Flagged as a conflict risk: a vendor that models FTE differently will fight the branch. | U5: Do per-diem and contract clinicians carry an FTE value at all, or are they null? | V5: Structural | W5: Control | X5: Branch | Y5: In-system | Z5: Workday | AA5: Quantitative | AB5: High | AC5: SHD-A | AD5: 3 | AE5: Y
A6: C-01 | B6: Capacity Management | D6: Workforce supply | E6: Aligned | F6: Headcount by discipline and employment type | G6: The staffed supply cut both ways at once — how many RNs are full-time, how many are per-diem, and so on. The single largest driver of what a branch can deliver. | H6: HR / Talent — maintains the record | I6: Branch Leadership (ED) — at staffing and referral-acceptance decisions | J6: Workday — worker record, rolled up | K6: High | L6: Automate | M6: Branch Leadership (ED) | N6: Continuous | O6: Stable | P6: — | Q6: Yes | R6: Y | S6: Low | T6: A branch is only as capable as its thinnest discipline; this is the view that shows it. | U6: Who owns the branch roll-up today — is anyone producing this view at all? | V6: Structural | W6: Control | X6: Branch | Y6: In-system | Z6: Workday | AA6: Quantitative | AB6: High | AC6: CAP-A | AD6: 3 | AE6: Y
A7: C-09 | B7: Capacity Management | C7: Engagement | D7: Workforce supply | E7: Aligned | F7: Per-diem and float pool | G7: The flex staff a branch can call on when its core team is full. Per-diem and float clinicians deliberately have no territory — that is what makes them a targeted instrument, used either to absorb admissions or to free a territory clinician for coverage. | H7: Scheduler and DCS — work the per-diem list by call, text and Teams | I7: DCS — decides when to spend the float lever | J7: Stated availability lives with the scheduler — a list, a spreadsheet or memory. HCHB holds who they are, not what they will take. | K7: Low | L7: Surface | M7: DCS — decides who to ask and when | N7: On event — call-outs and admission spikes | O7: Drifts — needs re-contact | P7: Weekly — when the week is built | Q7: Yes | R7: Y | S7: High | T7: The size of the buffer is legible; whether it actually flexes is relational. The system can show who is available, never assume they will say yes. | U7: Is there a maintained per-diem availability list anywhere, or is it rebuilt from memory each time? | V7: Structural | W7: Assist | X7: Branch | Y7: Manual | Z7: Manual + HCHB | AA7: Quantitative | AB7: Medium | AC7: CAP-E | AD7: 3 | AE7: N
A8: C-10 | B8: Capacity Management | C8: Scheduling | D8: Workforce supply | E8: Aligned | F8: Specialty competency supply | G8: How many clinicians can perform the visits that need more than a licence — wound, IV and infusion, catheter, ventilator, paediatric. Fourteen RNs but only three wound-certified means wound capacity, not RN capacity, is the real constraint. | H8: — partly HR (formal certs), partly nobody (informal competency) | I8: Clinical Manager — knows who is genuinely capable | J8: Workday holds formal licences and certifications. Informal competency lives in the Clinical Manager's head. | K8: Low | L8: Surface | M8: Clinical Manager — confirms who is genuinely competent | N8: Slow-changing — on certification or experience | O8: Drifts — needs re-contact | P8: Not re-checked today | Q8: Maybe | R8: N | S8: Medium | T8: Competency lives partly in reputation, not credentials. Surfacing it is useful; scoring it is not. | U8: Is there a competency list per clinician anywhere today, and who would own keeping it current? | V8: Structural | W8: Assist | X8: Clinician | Y8: Tacit | Z8: Workday + Manual | AA8: Quantitative | AB8: Medium | AC8: CAP-F | AD8: 1 | AE8: N
A9: C-11 | B9: Capacity Management | D9: Workforce supply | E9: Aligned | F9: Orientation and ramp status | G9: New hires count as headcount long before they carry a full load. Ignoring the ramp overstates supply — a week-two hire is not a full clinician. | H9: HR / Talent — records hire date and orientation status | I9: Clinical Manager — judges when someone is genuinely at full load | J9: Workday — hire date and orientation status. The ramp curve itself is not recorded anywhere. | K9: Medium | L9: Assist | M9: Clinical Manager — confirms the real ramp position | N9: Weekly during onboarding | O9: Stable | P9: — | Q9: Maybe | R9: N | S9: Low | T9: Headcount is clear; the true ramp curve is judgment. A system can propose a curve, a manager corrects it. | U9: Is there a standard ramp expectation by discipline, or is it manager-by-manager? | V9: Structural | W9: Assist | X9: Branch | Y9: In-system | Z9: Workday | AA9: Quantitative | AB9: Medium | AC9: CAP-G | AD9: 1 | AE9: N
A10: C-12 | B10: Capacity Management | C10: Scheduling | D10: Workforce supply | E10: Aligned | F10: On-call and weekend rotation load | G10: Work carried outside the standard week. A clinician coming off a weekend rotation starts Monday already partly loaded — if the schedule ignores it, the week is over-packed from day one. | H10: Scheduler — maintains the rotation | I10: Clinical Manager — balances the rotation across the team | J10: HCHB — on-call / rotation schedule | K10: Medium | L10: Automate | M10: Clinical Manager — owns rotation fairness | N10: Weekly | O10: Stable | P10: — | Q10: Yes | R10: Y | S10: Medium | T10: Legible load once the rotation is recorded. The fairness question is human. | U10: Is the rotation kept in HCHB, or on a separate branch calendar? | V10: Structural | W10: Control | X10: System | Y10: In-system | Z10: HCHB | AA10: Quantitative | AB10: High | AC10: CAP-C | AD10: 3 | AE10: N
A11: S-12 | B11: Capacity Management | C11: Scheduling, Engagement | D11: Workforce supply | E11: Aligned | F11: Willingness to flex | G11: How readily an individual clinician bends their pattern when asked — takes the extra visit, covers outside their territory, moves a day. It is the variable that decides which soft rules can actually be bent under pressure. | H11: Scheduler and DCS — learn it by asking, over time | I11: Scheduler — decides who to ask first | J11: Nobody's system. It lives in the scheduler's and DCS's working knowledge of their team. | K11: Low | L11: Surface | M11: Scheduler / DCS — decide who to approach | N11: On event — coverage and surge | O11: Drifts — needs re-contact | P11: On event — coverage and surge | Q11: Maybe | R11: N | S11: High | T11: A purely relational variable: the act of automating it changes what it measures. Surface who has said yes before; never auto-assign on it. | U11: Would clinicians accept this being visible at all? This is a trust question before it is a data question. | V11: Soft | W11: Read | X11: Clinician | Y11: Tacit | Z11: Manual | AA11: Qualitative | AB11: Low | AC11: SCH-C | AD11: 1 | AE11: N
A12: S-13 | B12: Capacity Management | C12: Engagement | D12: Workforce supply | E12: Aligned | F12: Willingness to take extra visits or overtime | G12: Whether a clinician will go beyond target, and on what terms. Strongly tied to pay model — a per-visit clinician has a reason to say yes that a salaried one does not. | H12: Scheduler — asks, one clinician at a time | I12: Scheduler / DCS — decide who to approach for coverage | J12: Nobody's system. Pay model is in Workday; willingness is not recorded anywhere. | K12: Low | L12: Surface | M12: Scheduler / DCS | N12: On event — coverage and surge | O12: Drifts — needs re-contact | P12: On event — coverage and surge | Q12: Maybe | R12: N | S12: High | T12: Relational and pay-linked. This is the row that connects to the incentives idea in the one-pager: today there is no mechanism, only a phone call. | U12: If we attach an incentive to hard-to-fill visits, who sets it and who approves the spend? | V12: Soft | W12: Read | X12: Clinician | Y12: Tacit | Z12: Manual | AA12: Qualitative | AB12: Low | AC12: SCH-C | AD12: 1 | AE12: N
A13: SH-05 | B13: Capacity Management | C13: Scheduling | D13: Availability & reach | E13: Aligned | F13: Approved time off and working availability | G13: The days each clinician is not available, and the pattern they normally work. The cleanest shared fact in the whole model: it removes capacity and removes a schedulable slot at the same moment. | H13: Clinician requests it; HR / manager approves it | I13: Scheduler — works around it when building the week | J13: Workday — time-off record. NOTE: the Workday-to-HCHB integration is currently OFF, so availability is re-entered by hand in HCHB. | K13: High | L13: Automate | M13: Scheduler — owns the exception when it is late or missing | N13: Continuous — as requests are approved | O13: Stable | P13: — | Q13: Yes | R13: Y | S13: Low | T13: A firm blackout once it is in the field. The integration being off is the single highest-value plumbing fix on this sheet — it makes every capacity number stale. | U13: What would it take to turn the Workday-to-HCHB availability integration back on? | V13: Hard | W13: Control | X13: Clinician | Y13: In-system | Z13: Workday + HCHB | AA13: Quantitative | AB13: High | AC13: SHD-B | AD13: 3 | AE13: N
A14: SH-06 | B14: Capacity Management | C14: Scheduling | D14: Availability & reach | E14: Aligned | F14: Territory and service area | G14: Where the branch is responsible for covering, and which of that area each clinician works. Capacity in the wrong place is stranded capacity — it exists but cannot reach the patient. | H14: Branch Leadership and DCS — set the lines | I14: Branch Leadership (ED) — reviews alignment when capacity tightens | J14: HCHB holds branch coverage; clinician zip assignment is part HCHB, part local knowledge. | K14: Medium | L14: Assist | M14: Branch Leadership (ED) — approves any territory change | N14: Quarterly, or when capacity tightens | O14: Stable | P14: — | Q14: Yes | R14: Y | S14: Medium | T14: Territory lines look fixed but encode local knowledge and standing agreements. A tool should propose changes, never redraw them. | U14: Is the current zip-to-clinician assignment complete in HCHB, or does the scheduler hold part of it? | V14: Structural | W14: Assist | X14: Geography | Y14: Manual | Z14: HCHB + Manual + Census | AA14: Quantitative | AB14: Medium | AC14: SHD-C | AD14: 3 | AE14: Y
A15: C-02 | B15: Capacity Management | D15: Availability & reach | E15: Aligned | F15: Branch coverage territory | G15: The counties the branch has committed to serve. Sets the outer boundary — a gap here is a coverage hole no amount of scheduling can fill. | H15: Branch Leadership — sets it | I15: Branch Leadership (ED) — at growth and referral decisions | J15: HCHB — branch configuration | K15: High | L15: Automate | M15: Branch Leadership (ED) | N15: Config — set once, revisited rarely | O15: Stable | P15: — | Q15: Yes | R15: Y | S15: Low | T15: Fixed boundary, cleanly held in configuration. | U15: Does the recorded coverage area match what the branch actually accepts in practice? | V15: Structural | W15: Control | X15: Geography | Y15: In-system | Z15: HCHB | AA15: Quantitative | AB15: High | AC15: CAP-B | AD15: 3 | AE15: N
A16: C-03 | B16: Capacity Management | C16: Scheduling | D16: Availability & reach | E16: Aligned | F16: Clinician territory assignment | G16: Which zip codes each clinician covers. Territories were originally drawn on thin data and have stayed largely static, with no live relationship to where referrals are actually coming from — so capacity drifts away from demand quietly. | H16: DCS and Scheduler — assign and adjust | I16: Branch Leadership (ED) with DCS — at the joint review when capacity tightens | J16: HCHB holds the assignment where it has been entered; the working version is often the scheduler's own reference. | K16: Medium | L16: Assist | M16: Branch Leadership (ED) with DCS | N16: Quarterly, or on demand shift | O16: Stable | P16: — | Q16: Yes | R16: Y | S16: High | T16: Called out in the inventory as the initial variable in the whole equation. Pairing it with a live census heat-map is the highest-leverage capacity change identified. | U16: How current is the zip assignment in HCHB right now — and when was it last reviewed against referral patterns? | V16: Structural | W16: Assist | X16: Geography | Y16: Manual | Z16: HCHB + Manual | AA16: Quantitative | AB16: Medium | AC16: CAP-B | AD16: 3 | AE16: Y
A17: C-04 | B17: Capacity Management | D17: Availability & reach | E17: Aligned | F17: Census-tract precision | G17: Whether to model coverage at a finer grain than zip. One large zip can span an urban core and a rural edge with completely different drive times, so the zip average misleads in both directions. | H17: — not done today | I17: Initiative team — a modelling decision, not an operational one | J17: Not in any system. Census data is public; the decision is ours. | K17: Medium | L17: Assist | M17: Initiative team — decide once, deliberately | N17: One-time decision | O17: Stable | P17: — | Q17: Yes | R17: Y | S17: Low | T17: A modelling choice, not a live control. It reshapes both the capacity map and the routing at once, so it should be decided on purpose rather than inherited from a vendor default. | U17: Do we want to make this call before vendor selection, or let the shortlist show us what is practical? | V17: Config | W17: Assist | X17: Geography | Y17: In-system | Z17: Census | AA17: Quantitative | AB17: Medium | AC17: CAP-B | AD17: 3 | AE17: Y
A18: C-14 | B18: Capacity Management | C18: Scheduling | D18: Availability & reach | E18: Aligned | F18: Territory currency | G18: Whether the territories are still right. C-03 records what each territory is; this records whether it still matches where the patients actually are, and how far the two have drifted. The drift is invisible until capacity is stranded in one zip while the area next to it turns work away. | H18: — not done today | I18: Branch Leadership (ED) with DCS — at the joint review when capacity tightens | J18: Not captured. It would come from comparing the territory assignment in HCHB against actual caseload and referral distribution. | K18: Low | L18: Assist | M18: Branch Leadership (ED) — redrawing a boundary is a leadership act | N18: Quarterly | O18: Live / computed | P18: — | Q18: Yes | R18: Y | S18: Medium | T18: Added 19 Aug. The workbook's own example is the whole argument: one territory carrying about thirty patients across two full-time clinicians while the adjacent area declines starts. The tool proposes the misalignment; a person moves the boundary. | U18: What cadence do we want for territory review, and who convenes it?
A19: S-46 | B19: Capacity Management | C19: Scheduling | D19: Availability & reach | E19: Aligned | F19: Achievable first-visit time | G19: The earliest visit a clinician can actually secure, as distinct from the time they would like to start. Nothing records the gap between the two — and that gap is the clearest measure of a day lost to the caseload rather than to any decision anyone made. | H19: — not measured today | I19: — no one today | J19: Not captured. It has to be asked, not inferred. | K19: Low | L19: Surface | M19: Clinical Manager — owns the gap as a problem to work | N19: Weekly | O19: Drifts — needs re-contact | P19: Weekly — when the week is built | Q19: Maybe | R19: N | S19: High | T19: Added 19 Aug, and deliberately read-only. Inferring the preference from observed start times would record defeat as choice and then optimise to preserve it. Ask, record the answer, report the gap. | U19: Who asks, and how often? This only works if the answer is collected rather than derived.
A20: C-05 | B20: Capacity Management | C20: Scheduling | D20: The capacity math | E20: Aligned | F20: Committed load — points already booked | G20: How much work is already on each clinician's calendar, in points. Capacity means nothing until you net this off: open room is the ceiling minus what is already committed. | H20: — the system holds it; nobody maintains it | I20: Scheduler — reads it while assigning; Clinical Manager — at productivity reviews | J20: HCHB — derived from booked visits; read through the scheduling and productivity views. | K20: Medium | L20: Automate | M20: Clinical Manager — acts on the imbalance | N20: Daily | O20: Live / computed | P20: — | Q20: Yes | R20: N | S20: Low | T20: Derived and safe to compute. The catch is pending-auth visits, which are on no calendar and count toward nothing — so this number is already understated today. | U20: Confirm which HCHB view the branch actually uses for committed points, and whether pending-auth visits appear anywhere in it. | V20: Derived | W20: Control | X20: System | Y20: In-system | Z20: Derived | AA20: Quantitative | AB20: High | AC20: CAP-C | AD20: 3 | AE20: N
A21: C-06 | B21: Capacity Management | C21: Scheduling | D21: The capacity math | E21: Aligned | F21: Open room by day | G21: How many bookable points are left in each day once assigned work is subtracted. The operational read of capacity — green means space, red means the day is full. | H21: — not produced as a view today | I21: — no one systematically; the scheduler infers it while assigning | J21: Not produced today. It would be derived from committed load against the daily ceiling. | K21: Low | L21: Automate | M21: Scheduler — acts on it daily; Clinical Manager — on the pattern | N21: Daily | O21: Live / computed | P21: — | Q21: Yes | R21: Y | S21: Low | T21: Pure derivation, but only as good as the point definitions underneath it. This is one of the clearest 'nobody can see this today' rows. | U21: Does any current HCHB view show open points by day, or is this genuinely net-new? | V21: Derived | W21: Control | X21: System | Y21: In-system | Z21: Derived | AA21: Quantitative | AB21: High | AC21: CAP-D | AD21: 3 | AE21: Y
A22: C-07 | B22: Capacity Management | D22: The capacity math | E22: Aligned | F22: Open capacity for the rest of the week | G22: The 'how much more can we take this week' number — the one a branch leader actually acts on when deciding whether to accept a referral. | H22: — not produced as a view today | I22: Branch Leadership (ED) — would own the decision it feeds | J22: Not produced today. | K22: Low | L22: Automate | M22: Branch Leadership (ED) — referral acceptance | N22: Daily | O22: Live / computed | P22: — | Q22: Yes | R22: N | S22: Low | T22: The headline capacity number. Everything else on this sheet exists to make it trustworthy. | U22: What is the decision this number should drive, and who makes it — ED, DCS, or intake? | V22: Derived | W22: Control | X22: System | Y22: In-system | Z22: Derived | AA22: Quantitative | AB22: High | AC22: CAP-D | AD22: 3 | AE22: N
A23: C-08 | B23: Capacity Management | C23: Scheduling | D23: The capacity math | E23: Aligned | F23: Admission capacity by discipline | G23: Open capacity limited to the clinicians who can actually open a case. New patients can only be absorbed by assessing staff, so this — not total capacity — is what gates growth. | H23: — not produced as a view today | I23: Branch Leadership (ED) and DCS — at referral acceptance | J23: Not produced today. | K23: Low | L23: Automate | M23: Branch Leadership (ED) / DCS | N23: Daily | O23: Live / computed | P23: — | Q23: Yes | R23: Y | S23: Low | T23: The growth-gating number. Distinct from total open room and more binding. | U23: How does the branch decide today whether it can take another admission — what is the current proxy? | V23: Derived | W23: Control | X23: System | Y23: In-system | Z23: Derived | AA23: Quantitative | AB23: High | AC23: CAP-D | AD23: 3 | AE23: Y
A24: SH-07 | B24: Capacity Management | C24: Scheduling | D24: The capacity math | E24: Aligned | F24: Visit weighting — the point value of each visit type | G24: The shared currency. A start of care is worth more than a routine visit, so the same headcount delivers different capacity depending on the mix of work. Everything in capacity and productivity is denominated in these points. | H24: Corporate / Operations — sets the values | I24: Clinical Manager and Branch Leadership — read productivity against them | J24: HCHB holds point values per visit type; the surrounding policy sits in branch and corporate configuration. | K24: Medium | L24: Automate | M24: Corporate / Operations — owns the definition | N24: Config — set once, revisited by policy | O24: Stable | P24: — | Q24: Yes | R24: N | S24: Medium | T24: The values exist. What is undefined is how travel, documentation time and acuity are treated — and until that is settled, every derived capacity number inherits the ambiguity. | U24: Open question #1: do points account for travel, documentation and acuity, or only visit type? | V24: Config | W24: Control | X24: System | Y24: In-system | Z24: Config | AA24: Quantitative | AB24: High | AC24: SHD-D | AD24: 3 | AE24: Y
A25: SH-08 | B25: Capacity Management | D25: The capacity math | E25: Aligned | F25: Targets and ceilings | G25: The weekly load a clinician is expected to carry and the daily maximum they should not exceed. The target is what we plan toward; the ceiling is what capacity cannot cross. | H25: Corporate / Operations — sets it | I25: Clinical Manager — manages individuals against it | J25: HCHB productivity settings plus branch policy. | K25: Medium | L25: Automate | M25: Clinical Manager | N25: Config | O25: Stable | P25: — | Q25: Yes | R25: N | S25: Medium | T25: A policy constant and a simple lookup. Conflict risk: a vendor with its own opinion about targets will fight branch policy. | U25: Are targets uniform across branches and disciplines, or do they vary? | V25: Config | W25: Control | X25: Branch | Y25: In-system | Z25: HCHB + Config | AA25: Quantitative | AB25: High | AC25: SHD-E | AD25: 3 | AE25: Y
A26: SH-09 | B26: Capacity Management | C26: Scheduling | D26: The capacity math | E26: Aligned | F26: Referrals coming in, discharges going out | G26: The two events that move the envelope. A referral consumes capacity when it is assigned; a discharge hands it back. Reading them together is how you see capacity as a shape over the next few weeks rather than a number today. | H26: Intake — receives referrals; Clinician — performs the discharge | I26: Branch Leadership (ED) — reads the balance | J26: Referrals arrive in Commure and land in HCHB; discharges are in HCHB. | K26: Medium | L26: Automate | M26: Branch Leadership (ED) | N26: Continuous — as events occur | O26: Stable | P26: — | Q26: Yes | R26: N | S26: Low | T26: Detecting the events is straightforward. What to do about the trend is the judgment, and it sits with the branch. | U26: Is discharge date reliable enough in HCHB to forecast returning capacity? | V26: Event | W26: Control | X26: System | Y26: In-system | Z26: HCHB | AA26: Quantitative | AB26: High | AC26: SHD-F | AD26: 3 | AE26: N
A27: C-13 | B27: Capacity Management | D27: The capacity math | E27: Aligned | F27: Referral volume (held out of scope) | G27: The rate of incoming referrals. Recorded here for completeness and deliberately not treated as a lever in this initiative — it belongs to intake and growth, not to capacity and scheduling. | H27: Intake — receives them | I27: Growth / Branch Leadership — outside this initiative | J27: Commure and HCHB. | K27: Medium | L27: Stays manual | M27: — outside this initiative | N27: Continuous | O27: Stable | P27: — | Q27: No | R27: N | S27: Low | T27: Out of scope by choice, documented so the capacity math is transparent about what it holds constant. | U27: Confirm this stays out of scope as the initiative moves into future-state design. | V27: Context | W27: Read | X27: System | Y27: In-system | Z27: HCHB | AA27: Quantitative | AB27: Low | AC27: CAP-H | AD27: 0 | AE27: N
A28: S-04 | B28: Capacity Management | C28: Capacity | D28: Matching | E28: Differs — the one-pager groups this under Scheduling Engine | F28: Preferred working days | G28: The days each clinician normally works, including rotations like four long days or a standing Friday off. Baseline availability that scheduling has to respect. | H28: Clinician — states it; Scheduler — holds it | I28: Scheduler | J28: Partly HCHB, partly the scheduler's own knowledge. Rotations and swaps are handled informally. | K28: Low | L28: Assist | M28: Scheduler | N28: Slow-changing, with informal exceptions | O28: Drifts — needs re-contact | P28: Weekly — when the week is built | Q28: Maybe | R28: N | S28: Medium | T28: A set pattern with informal exceptions — the exceptions are the part no system holds. | U28: Are working patterns recorded in HCHB per clinician, or reconstructed by the scheduler each week? | V28: Soft | W28: Assist | X28: Clinician | Y28: Tacit | Z28: Manual + HCHB | AA28: Qualitative | AB28: Medium | AC28: SCH-C | AD28: 1 | AE28: N
A29: S-05 | B29: Capacity Management | D29: Matching | E29: Differs — the one-pager groups this under Scheduling Engine | F29: Preferred start time | G29: When a clinician likes to begin. It anchors the front of the route, and the first visit of the day is the single largest lever on an individual's capacity — an 8am start and a 10am start are very different days. | H29: Clinician — states it | I29: Scheduler — decides how far to accommodate | J29: Nobody's system — the scheduler's working knowledge. | K29: Low | L29: Assist | M29: Scheduler | N29: Daily, in practice | O29: Drifts — needs re-contact | P29: Weekly — when the week is built | Q29: Maybe | R29: N | S29: High | T29: Preferred and possible are two different things. Many clinicians want an early first visit and struggle to make it happen; it takes planning and patient motivation, not just a preference field. | U29: Do we want to set a branch expectation on first-visit time, or keep it individual? | V29: Soft | W29: Assist | X29: Clinician | Y29: Tacit | Z29: Manual | AA29: Qualitative | AB29: Medium | AC29: SCH-C | AD29: 1 | AE29: N
A30: S-06 | B30: Capacity Management | D30: Matching | E30: Differs — the one-pager groups this under Scheduling Engine | F30: Start-time flexibility | G30: Whether that start time can move day to day. It separates a clinician who will shift to fit a patient window from one who cannot — which is a real scheduling lever, but only if they have told you. | H30: Clinician — decides in the moment | I30: Scheduler — asks | J30: Nobody's system. | K30: Low | L30: Surface | M30: Scheduler | N30: Daily | O30: Drifts — needs re-contact | P30: Day before — the confirmation round | Q30: Maybe | R30: N | S30: High | T30: Depends on a person's willingness. Assuming it is available damages the trust the whole thing runs on — surface only. | U30: None — this row is intentionally read-only. | V30: Soft | W30: Read | X30: Clinician | Y30: Tacit | Z30: Manual | AA30: Qualitative | AB30: Low | AC30: SCH-C | AD30: 1 | AE30: N
A31: S-07 | B31: Capacity Management | D31: Matching | E31: Differs — the one-pager groups this under Scheduling Engine | F31: Lunch and documentation pattern | G31: Whether a clinician holds time mid-day for a break or for charting. It removes a slot and splits the route into two halves. | H31: Clinician — their own habit | I31: Scheduler — builds around it | J31: Nobody's system. | K31: Low | L31: Assist | M31: Scheduler | N31: Daily | O31: Drifts — needs re-contact | P31: Weekly — when the week is built | Q31: Maybe | R31: N | S31: Medium | T31: A capturable personal habit. Worth knowing, not worth enforcing. | U31: Would clinicians be willing to record this, or does it feel like surveillance? | V31: Soft | W31: Assist | X31: Clinician | Y31: Tacit | Z31: Manual | AA31: Qualitative | AB31: Medium | AC31: SCH-C | AD31: 1 | AE31: N
A32: S-08 | B32: Capacity Management | D32: Matching | E32: Differs — the one-pager groups this under Scheduling Engine | F32: Mid-day documentation block | G32: Time reserved specifically for charting, usually mid-afternoon. It consumes schedulable time and shapes the day into segments. | H32: Clinician — their own habit | I32: Scheduler — builds around it | J32: Nobody's system. | K32: Low | L32: Assist | M32: Scheduler | N32: Daily | O32: Drifts — needs re-contact | P32: Weekly — when the week is built | Q32: Maybe | R32: N | S32: Medium | T32: Same shape as the lunch pattern. Note that documentation time is real capacity consumed, and today it is invisible in the point math. | U32: Should documentation time be represented in the point system? Ties to open question #1. | V32: Soft | W32: Assist | X32: Clinician | Y32: Tacit | Z32: Manual | AA32: Qualitative | AB32: Medium | AC32: SCH-C | AD32: 1 | AE32: N
A33: S-09 | B33: Capacity Management | D33: Matching | E33: Differs — the one-pager groups this under Scheduling Engine | F33: Split shift or mid-day personal break | G33: A gap in the middle of the day — school pickup, an errand — with visits either side. It creates a two-cluster day rather than a continuous one. | H33: Clinician — their own routine | I33: Scheduler — builds around it when told | J33: Nobody's system. | K33: Low | L33: Surface | M33: Scheduler | N33: Daily, and it varies | O33: Drifts — needs re-contact | P33: Day before — the confirmation round | Q33: Maybe | R33: N | S33: High | T33: A personal daily rhythm that varies. Hard to predict reliably and easily disrupted by a system that assumes it knows — read only. | U33: None — intentionally read-only. | V33: Soft | W33: Read | X33: Clinician | Y33: Tacit | Z33: Manual | AA33: Qualitative | AB33: Low | AC33: SCH-C | AD33: 1 | AE33: N
A34: S-10 | B34: Capacity Management | D34: Matching | E34: Differs — the one-pager groups this under Scheduling Engine | F34: Hard stop — when the day has to end | G34: The time a clinician must be finished by, usually for childcare or a second commitment. Once you know it, it behaves exactly like a hard rule; the difficulty is that knowing it depends on them telling you. | H34: Clinician — states it | I34: Scheduler — honours it | J34: Nobody's system. | K34: Low | L34: Assist | M34: Scheduler | N34: Daily | O34: Drifts — needs re-contact | P34: Weekly — when the week is built | Q34: Yes | R34: N | S34: Medium | T34: A firm edge once known. The knowing is the tacit part. | U34: Is there a place a clinician could record a standing hard stop today? | V34: Hard/Soft | W34: Assist | X34: Clinician | Y34: Tacit | Z34: Manual | AA34: Qualitative | AB34: Medium | AC34: SCH-C | AD34: 3 | AE34: N
A35: S-11 | B35: Capacity Management | D35: Matching | E35: Differs — the one-pager groups this under Scheduling Engine | F35: Maximum visits in a day | G35: The most visits an individual will carry before the day stops working, regardless of what the points allow. It bounds how densely a day can be packed. | H35: Clinician — states it | I35: Scheduler — respects it | J35: Nobody's system. | K35: Low | L35: Assist | M35: Scheduler | N35: Slow-changing | O35: Drifts — needs re-contact | P35: Weekly — when the week is built | Q35: Maybe | R35: N | S35: Medium | T35: A personal ceiling, capturable and worth confirming. Conflict risk: a vendor that packs to points alone will breach it. | U35: Do we want a branch-level maximum as well as an individual one? | V35: Soft | W35: Assist | X35: Clinician | Y35: Tacit | Z35: Manual | AA35: Qualitative | AB35: Medium | AC35: SCH-C | AD35: 1 | AE35: Y
A36: S-14 | B36: Scheduling Engine | C36: Scheduling | D36: Availability & reach | E36: Differs — the one-pager groups this under Capacity Management | F36: Home base — where the day starts and ends | G36: The point each clinician drives from and returns to. A first visit far from home wastes the front of the day, which is the most productive part of it. | H36: — captured informally, if at all | I36: Scheduler and Clinician — when building the route | J36: Home address is in Workday. Whether it is usable for drive-time is unconfirmed; routing today works off manual knowledge. | K36: Low | L36: Automate | M36: Scheduler — confirms the anchor | N36: Slow-changing | O36: Stable | P36: — | Q36: Yes | R36: Y | S36: Medium | T36: A legible anchor once captured. Using home addresses for routing has a privacy dimension worth settling early. | U36: Can we use clinician home addresses for drive-time calculation, and has that been agreed with them? | V36: Structural | W36: Control | X36: Geography | Y36: Manual | Z36: Manual + Routing | AA36: Quantitative | AB36: High | AC36: SCH-D | AD36: 3 | AE36: N
A37: S-01 | B37: Scheduling Engine | D37: Demand | E37: Aligned | F37: Ordered visits and frequency | G37: What each discipline has ordered for a patient and how often — the demand signal at the visit level. Everything scheduling does is placing these orders into slots that work. | H37: Clinician — plots the frequency in the plan of care; DCS — approves it | I37: DCS — approves the plan of care before anything can be scheduled | J37: HCHB — plan of care and generated visits | K37: High | L37: Automate | M37: DCS — owns plan-of-care approval | N37: Per episode, at plan of care and at each recertification | O37: Stable | P37: — | Q37: Yes | R37: Y | S37: Low | T37: Clear in HCHB. Note that each discipline plots to clinical need without seeing payer limits at that moment — which is where the auth collision starts. | U37: Nothing outstanding — this row is solid. | V37: Hard | W37: Control | X37: Patient | Y37: In-system | Z37: HCHB | AA37: Quantitative | AB37: High | AC37: SCH-A | AD37: 3 | AE37: N
A38: S-02 | B38: Scheduling Engine | D38: Demand | E38: Aligned | F38: Visit type | G38: What kind of visit each one is — start of care, routine, recertification, resumption, discharge, supervisory. It sizes the slot and dictates who is allowed to perform it. | H38: — set by the order | I38: Scheduler — reads it when assigning | J38: HCHB — visit record | K38: High | L38: Automate | M38: — exception only | N38: Per visit | O38: Stable | P38: — | Q38: Yes | R38: Y | S38: Low | T38: Clean order attribute. | U38: Nothing outstanding. | V38: Hard | W38: Control | X38: Patient | Y38: In-system | Z38: HCHB | AA38: Quantitative | AB38: High | AC38: SCH-A | AD38: 3 | AE38: N
A39: S-43 | B39: Scheduling Engine | C39: Capacity | D39: Demand | E39: Aligned | F39: Insurance authorization | G39: Whether the payer has agreed to pay for the visits, and how many. It behaves two completely different ways: at admission it is a gate — nothing schedules until it clears — and inside the episode it is a silent ceiling checked visit by visit. | H39: Auth team — verifies eligibility and keys the pending auth; Intake — gives final approval | I39: Auth team, then Intake — and the Scheduler holds what is stuck | J39: HCHB holds auth status per visit; the referral side sits in Commure. The payer's actual rules are written by the auth team into a coordination note at verification — days before anyone writes the plan of care. | K39: Medium | L39: Automate | M39: Scheduler — owns what falls out; Auth team — owns the exception | N39: Per episode and per add-on order | O39: Stable | P39: — | Q39: Yes | R39: Y | S39: Medium | T39: The largest single bottleneck in current-state scheduling, and the most tractable: the rules already exist in writing before they are needed. Surfacing the coordination note at plan-of-care creation is the highest-value, lowest-complexity win identified. Pending-auth visits sit on no calendar and count toward nothing — if you cannot see it, you cannot plan it. | U39: Can the auth coordination note be surfaced into the plan-of-care screen, and who owns that change?
A40: S-44 | B40: Scheduling Engine | C40: Capacity | D40: Demand | E40: Aligned | F40: Add-on orders | G40: Any order written after the plan of care is submitted. In steady state there is no recurring scheduler workflow at all unless an add-on changes the frequency — at which point it routes through DCS approval, then authorization, then back to the scheduler, for every affected discipline. | H40: Clinician — requests; DCS — reviews | I40: DCS — decides, then it returns to the auth loop | J40: HCHB — orders. The DCS review workflow itself is described as still being defined. | K40: Low | L40: Assist | M40: DCS | N40: On event — mid-episode | O40: Stable | P40: — | Q40: Yes | R40: Y | S40: Medium | T40: Flagged in the inventory as a bottleneck awaiting DCS workflow. It affects how capacity looks as well as what gets scheduled. | U40: What is the current DCS add-on workflow, and is it consistent across branches?
A41: S-03 | B41: Scheduling Engine | D41: Demand | E41: Aligned | F41: Ordered-frequency window | G41: The date range each ordered visit has to land inside. A visit delivered outside its window is a compliance miss even though the care happened. | H41: — HCHB applies the rule | I41: Scheduler — works to it; Clinical Manager — on exceptions | J41: HCHB — calculated from the order | K41: High | L41: Automate | M41: Scheduler — owns the exception | N41: Per visit | O41: Live / computed | P41: — | Q41: Yes | R41: Y | S41: Low | T41: A hard, legible clock — among the safest things to enforce automatically. | U41: Nothing outstanding. | V41: Hard | W41: Control | X41: System | Y41: In-system | Z41: HCHB | AA41: Quantitative | AB41: High | AC41: SCH-B | AD41: 3 | AE41: N
A42: S-35 | B42: Scheduling Engine | C42: Capacity | D42: Demand | E42: Aligned | F42: Start-of-care timing window | G42: The clock that starts when a referral is accepted. Every start of care is time-sensitive — seen within 48 hours under Medicare guidelines. 'Urgent' does not mean time-sensitive; it means a clinical priority flag on top of an already-tight clock. | H42: Scheduler — books it inside the window | I42: Scheduler; DCS — when it is at risk | J42: HCHB — referral and visit dates | K42: High | L42: Automate | M42: Scheduler; escalates to DCS | N42: Per referral | O42: Live / computed | P42: — | Q42: Yes | R42: Y | S42: Low | T42: A hard regulatory clock, fully clear — described in the inventory as the safest automation win available. | U42: Nothing outstanding. | V42: Hard | W42: Control | X42: System | Y42: In-system | Z42: HCHB | AA42: Quantitative | AB42: High | AC42: SCH-B | AD42: 3 | AE42: N
A43: S-36 | B43: Scheduling Engine | D43: Demand | E43: Aligned | F43: Recertification and face-to-face windows | G43: The windows that bind the end of an episode — the recertification visit must fall in the last five days, and the face-to-face encounter has its own requirement. They bind only the disciplines that are actually recertifying. | H43: — HCHB applies the rule; Clinician performs the visit | I43: Clinician — decides whether to recertify; DCS — approves | J43: HCHB — episode dates and visit records | K43: High | L43: Automate | M43: DCS | N43: Per episode | O43: Live / computed | P43: — | Q43: Yes | R43: Y | S43: Low | T43: Regulatory window; enforce and flag. Recert visits are already on the calendar from the original plan of care. | U43: Nothing outstanding. | V43: Hard | W43: Control | X43: System | Y43: In-system | Z43: HCHB | AA43: Quantitative | AB43: High | AC43: SCH-B | AD43: 3 | AE43: N
A44: S-49 | B44: Scheduling Engine | C44: Capacity | D44: Demand | E44: Aligned | F44: How far behind the review queues are | G44: The depth and age of the plan-of-care QA queue and the physician-order approval queue. QA is a hard stop — nothing schedules until it clears — so when the queue runs behind, an assistant waits and a week of care compresses into a few days. | H44: QA and Clinical Manager — work the queue | I44: — no one downstream can see it today | J44: HCHB holds the queues. Their depth and age are not surfaced to the people they block. | K44: Medium | L44: Surface | M44: DCS — escalates when the queue is the constraint | N44: Daily | O44: Live / computed | P44: — | Q44: Yes | R44: Y | S44: Low | T44: Added 19 Aug. Queue depth and age are countable, but the queue is other people's work — surface it in front of the people it blocks, do not reorder it. | U44: Can queue age be reported daily, and who owns acting on it?
A45: S-15 | B45: Scheduling Engine | D45: Matching | E45: Aligned | F45: Discipline and role match | G45: Putting the visit with someone licensed to perform it. The one genuine hard gate the system enforces by itself — an RN start of care cannot go to a physiotherapy assistant. | H45: — HCHB enforces it | I45: Scheduler — works inside it | J45: HCHB — derived from discipline and visit type | K45: High | L45: Automate | M45: — exception only | N45: Per visit | O45: Live / computed | P45: — | Q45: Yes | R45: Y | S45: High | T45: A hard gate and fully legible. The sensitivity is the flip side: auto-assigning routine visits to assistants opens a lot of capacity but is a significant change-management conversation. | U45: How far do we want to push routine visits to assistants, and who owns that decision? | V45: Hard | W45: Control | X45: System | Y45: In-system | Z45: Derived | AA45: Quantitative | AB45: High | AC45: SCH-E | AD45: 3 | AE45: N
A46: S-16 | B46: Scheduling Engine | C46: Capacity | D46: Matching | E46: Aligned | F46: Specialty competency match | G46: Sending visits that need a specific skill to someone who actually has it. It narrows the eligible pool well below the discipline — a hidden hard constraint that only shows up when the match fails. | H46: Scheduler — matches by hand, from knowledge | I46: Scheduler; Clinical Manager — when it is not obvious | J46: Formal certifications in Workday; the working knowledge of who can do what sits with the Clinical Manager and Scheduler. | K46: Low | L46: Assist | M46: Clinical Manager — confirms competency | N46: Per visit | O46: Stable | P46: — | Q46: Yes | R46: Y | S46: Medium | T46: Only as good as the competency data, which is incomplete today. This is human work performed on information the system does not hold. | U46: Would we build a competency register, and who maintains it? | V46: Hard | W46: Assist | X46: System | Y46: Manual | Z46: Workday + Manual | AA46: Quantitative | AB46: Medium | AC46: SCH-E | AD46: 3 | AE46: N
A47: S-33 | B47: Scheduling Engine | D47: Matching | E47: Aligned | F47: Matching acuity to skill level | G47: Sending a more complex patient to a more capable clinician. This is clinical judgment, not a rule — the system can recommend, but a person has to own it. | H47: Scheduler — with Clinical Manager input | I47: Clinical Manager — owns the judgment | J47: Acuity signals sit in HCHB; the judgment itself is not recorded. | K47: Low | L47: Surface | M47: Clinical Manager | N47: Per visit, especially at admission | O47: Drifts — needs re-contact | P47: At recertification | Q47: Yes | R47: Y | S47: Medium | T47: Clinical judgment with patient-safety consequences. Recommend, never decide. Useful for triage when coverage is short. | U47: Do we have any usable acuity measure today, or is it entirely judgment? | V47: Hard | W47: Read | X47: System | Y47: Tacit | Z47: HCHB + Manual | AA47: Quantitative | AB47: Low | AC47: SCH-E | AD47: 3 | AE47: N
A48: S-21 | B48: Scheduling Engine | D48: Matching | E48: Aligned | F48: Clinician restrictions | G48: Firm limits on what an individual can be given — no wound care, north territory only, no more than a certain acuity. Set by the branch, and treated as absolute once set. | H48: Clinical Manager / DCS — set them | I48: Scheduler — works inside them | J48: Not consistently in a system; typically manual, held by the scheduler and Clinical Manager. | K48: Low | L48: Automate | M48: Clinical Manager — owns the restriction | N48: Slow-changing | O48: Stable | P48: — | Q48: Yes | R48: Y | S48: Medium | T48: A documented hard gate the system should simply honour — but only once it is actually written down somewhere the system can read. | U48: Where are clinician restrictions recorded today? This may be the easiest structured-data win on the sheet. | V48: Hard | W48: Control | X48: Clinician | Y48: Tacit | Z48: Manual | AA48: Qualitative | AB48: High | AC48: SCH-F | AD48: 3 | AE48: N
A49: S-22 | B49: Scheduling Engine | C49: Engagement | D49: Matching | E49: Aligned | F49: Continuity of care | G49: Keeping the same clinician with a patient across the episode. It improves outcomes and satisfaction, and the relationship carries real clinical value — but that value is invisible in the data, so an optimiser will trade it away unless told not to. | H49: Scheduler — protects it when assigning | I49: Scheduler; Clinician — raises it when broken | J49: HCHB records who has seen the patient; the importance of keeping them is not recorded. | K49: Medium | L49: Assist | M49: Scheduler | N49: Per visit | O49: Stable | P49: — | Q49: Maybe | R49: N | S49: Medium | T49: Load-bearing but invisible. Protect it explicitly rather than scoring it against efficiency. | U49: How much continuity are we willing to trade for routing efficiency? A policy call, not a technical one. | V49: Soft | W49: Assist | X49: Patient | Y49: In-system | Z49: HCHB | AA49: Qualitative | AB49: Medium | AC49: SCH-G | AD49: 1 | AE49: N
A50: S-37 | B50: Scheduling Engine | D50: Matching | E50: Aligned | F50: Supervisory visit dependency | G50: Required supervision visits on a set cadence — an RN must supervise an aide's patient every fourteen days. It chains one person's schedule to another's, which is different from a single assignment. | H50: — HCHB generates it; Clinician performs it | I50: Scheduler — places it; Clinical Manager — on compliance | J50: HCHB — rule-driven visit generation | K50: High | L50: Automate | M50: Scheduler | N50: Per cadence — typically 14 days | O50: Live / computed | P50: — | Q50: Yes | R50: Y | S50: Low | T50: Rule-based and legible. | U50: Nothing outstanding. | V50: Hard | W50: Control | X50: System | Y50: In-system | Z50: HCHB | AA50: Quantitative | AB50: High | AC50: SCH-L | AD50: 3 | AE50: N
A51: S-31 | B51: Scheduling Engine | D51: Matching | E51: Aligned | F51: Clinically driven timing | G51: Timing set by the medicine, not by preference — a fasting lab in the morning, an insulin-teaching visit aligned to the patient's dose, a wound cadence. It looks like a preference and is not. | H51: Clinician — determines it | I51: Clinician — owns it | J51: Clinical detail in HCHB; the scheduling consequence usually in the coordination note. | K51: Medium | L51: Surface | M51: Clinician | N51: Per visit for affected patients | O51: Drifts — needs re-contact | P51: Weekly — when the week is built | Q51: Yes | R51: Y | S51: Medium | T51: Clinical judgment with patient-safety consequences — flag it, never decide it. Also the clearest place where a rehospitalisation-risk signal would earn its keep. | U51: Could clinically driven timing be flagged distinctly from preference in the record? | V51: Hard | W51: Read | X51: Patient | Y51: Tacit | Z51: HCHB + Manual | AA51: Quantitative | AB51: Low | AC51: SCH-K | AD51: 3 | AE51: N
A52: S-34 | B52: Scheduling Engine | D52: Matching | E52: Aligned | F52: Infection-control sequencing | G52: The order visits are taken in when infection risk is involved — the immunocompromised patient seen before the infectious one, never after. | H52: Clinician — sequences their own day | I52: Clinician | J52: Not recorded; applied by the clinician from clinical knowledge. | K52: Low | L52: Assist | M52: Clinician | N52: Daily, when applicable | O52: Drifts — needs re-contact | P52: Day before — the confirmation round | Q52: Maybe | R52: N | S52: Low | T52: Partly rule, partly judgment. A system can propose the sequence and flag conflicts; the clinician confirms. | U52: Are there written sequencing rules, or is this entirely clinician knowledge? | V52: Soft | W52: Assist | X52: Patient | Y52: Manual | Z52: Manual | AA52: Quantitative | AB52: Medium | AC52: SCH-K | AD52: 1 | AE52: N
A53: S-48 | B53: Scheduling Engine | D53: Matching | E53: Aligned | F53: Rehospitalisation risk | G53: How likely a patient is to end up back in hospital, used to decide which visits matter most. A scheduling input as much as a clinical one: it should decide which visit survives a call-out and which patient can tolerate a gap. | H53: — produced by Pulse | I53: — no one uses it for scheduling today | J53: Pulse. | K53: Medium | L53: Surface | M53: Clinical Manager / Clinician — decide priority | N53: Per patient, continuous | O53: Live / computed | P53: — | Q53: Maybe | R53: N | S53: Medium | T53: Added 19 Aug. A risk score may inform priority; it may not silently reorder a clinician's day or override clinical judgment. The natural companion to acuity matching when coverage is short. | U53: Is Pulse data reachable from scheduling today, and in what form?
A54: S-17 | B54: Scheduling Engine | C54: Capacity | D54: Routing & the week | E54: Aligned | F54: Closeness to the rest of the day's route | G54: Whether a candidate visit sits near the ones already booked. Clustering is the primary efficiency lever — it cuts drive time, which converts directly into more visits that fit in a day. | H54: Clinician — groups their own visits by drive time | I54: Clinician; Scheduler — at assignment | J54: HCHB suggests a route; the clinician adjusts it. Drive-time data itself is not held today. | K54: Medium | L54: Automate | M54: Clinician — adjusts the proposal | N54: Daily | O54: Live / computed | P54: — | Q54: Maybe | R54: N | S54: Low | T54: Geometry, and safely reversible. The efficiency gain here is real rather than borrowed from someone's slack. | U54: What routing data does HCHB actually use today — distance, or real drive time? | V54: Soft | W54: Control | X54: Geography | Y54: In-system | Z54: Routing | AA54: Quantitative | AB54: High | AC54: SCH-D | AD54: 1 | AE54: Y
A55: S-18 | B55: Scheduling Engine | C55: Capacity | D55: Routing & the week | E55: Aligned | F55: Route mileage | G55: The total driving in a sequenced day. It is the cost being minimised — high mileage means fewer visits fit, so mileage and capacity are the same conversation. | H55: — calculated by the routing function | I55: Clinical Manager / Branch Leadership — on cost and efficiency | J55: HCHB routing output; mileage also has a reimbursement and payroll dimension. | K55: Medium | L55: Automate | M55: Clinical Manager | N55: Daily | O55: Live / computed | P55: — | Q55: Yes | R55: N | S55: Low | T55: Deterministic routing maths. | U55: Is mileage currently reported anywhere the branch actually looks at? | V55: Derived | W55: Control | X55: Geography | Y55: In-system | Z55: Routing | AA55: Quantitative | AB55: High | AC55: SCH-D | AD55: 3 | AE55: N
A56: S-19 | B56: Scheduling Engine | D56: Routing & the week | E56: Aligned | F56: Order of visits within the day | G56: The sequence the day runs in. Fixed points — a caregiver window, a timed teaching visit — pin the route, and everything else fills around them. | H56: Clinician — sets their own order | I56: Clinician | J56: HCHB suggests; the clinician decides. The pinning constraints live in coordination notes. | K56: Medium | L56: Assist | M56: Clinician | N56: Daily | O56: Live / computed | P56: — | Q56: Maybe | R56: N | S56: Medium | T56: A legible skeleton pinned by tacit anchors. Propose the sequence; let the person place the anchors. | U56: Nothing outstanding. | V56: Soft | W56: Assist | X56: Geography | Y56: In-system | Z56: Derived | AA56: Quantitative | AB56: Medium | AC56: SCH-D | AD56: 1 | AE56: N
A57: S-20 | B57: Scheduling Engine | C57: Engagement | D57: Routing & the week | E57: Aligned | F57: Appointment time windows | G57: Committing to a band of time rather than just a day. It turns a day-level order into a time-level promise — which is what patients actually want, and what the branch is least able to give today. | H57: Clinician — agrees it on the confirmation call | I57: Clinician; Scheduler when booked centrally | J57: Partly HCHB, largely agreed verbally the day before. | K57: Low | L57: Assist | M57: Scheduler / Clinician | N57: Day before the visit | O57: Drifts — needs re-contact | P57: Day before — the confirmation round | Q57: Yes | R57: N | S57: High | T57: Enforceable once captured; capture is the weak point. Standardising this would move patient satisfaction and team efficiency together — and it is a visible change for clinicians. | U57: Do we want to move to committed time windows, and what would that cost in flexibility? | V57: Hard/Soft | W57: Assist | X57: Geography | Y57: Manual | Z57: HCHB + Manual | AA57: Quantitative | AB57: Medium | AC57: SCH-D | AD57: 3 | AE57: N
A58: S-45 | B58: Scheduling Engine | D58: Routing & the week | E58: Aligned | F58: Clinician safety | G58: Market-specific rules constraining when and where a visit may be scheduled, and the alerts a clinician must see before they go. These are requirements, not preferences: one market screens for firearms in the home, other people present, and mental illness — a rule instituted after a clinician was killed in a patient's home. | H58: Clinician — raises it; Branch Leadership — sets the rule | I58: Branch Leadership (ED) — owns the policy | J58: Not held in a system today; handled market by market. | K58: Low | L58: Assist | M58: Branch Leadership (ED) | N58: As raised, and by market rule | O58: Stable | P58: — | Q58: Maybe | R58: N | S58: Medium | T58: Numbered S-45 on 19 Aug. Where it applies the slot is removed from the route rather than flagged for override. Currently invisible to any scheduling logic, and it varies by market. | U58: Which markets have safety rules today, and where are they written down?
A59: S-40 | B59: Scheduling Engine | C59: Capacity | D59: Routing & the week | E59: Aligned | F59: Front-loading the week | G59: Concentrating visits early so a missed day later can still be recovered. The stated gold standard is around 42% of the week's work done by Tuesday night. | H59: Clinician — builds their own week | I59: Clinical Manager — reviews the pattern | J59: Derived from the schedule in HCHB. | K59: Medium | L59: Assist | M59: Clinical Manager | N59: Weekly | O59: Live / computed | P59: — | Q59: Maybe | R59: N | S59: Medium | T59: A target, not a law. Forcing it flattens the clinician's own rhythm, which costs more than it saves. | U59: Is 42% by Tuesday the standard we want to hold branches to? | V59: Soft | W59: Assist | X59: System | Y59: In-system | Z59: Derived | AA59: Quantitative | AB59: Medium | AC59: SCH-N | AD59: 1 | AE59: Y
A60: S-41 | B60: Scheduling Engine | C60: Capacity | D60: Routing & the week | E60: Aligned | F60: Pace against the plan | G60: Whether a clinician is on track against their own planned week so far. It is the early signal that tells you to rebalance on Wednesday rather than discover the problem on Friday. | H60: — derived | I60: Clinical Manager — acts on it; Scheduler — rebalances | J60: Derived from HCHB scheduled versus completed work. | K60: Medium | L60: Automate | M60: Clinical Manager | N60: Daily | O60: Live / computed | P60: — | Q60: Maybe | R60: N | S60: Low | T60: A derived read, safe to surface. This is the archetype of the pattern you described: the system can produce it, but somebody has to look and act. | U60: Who should own the daily pace read — Clinical Manager, Scheduler, or both? | V60: Derived | W60: Control | X60: System | Y60: In-system | Z60: Derived | AA60: Quantitative | AB60: High | AC60: SCH-N | AD60: 1 | AE60: N
A61: S-42 | B61: Scheduling Engine | C61: Capacity | D61: Routing & the week | E61: Aligned | F61: Balancing the week day by day | G61: Spreading work so no single day is over-packed and none is idle. It protects against both burnout days and wasted ones. | H61: Clinician — balances their own week | I61: Clinical Manager — on the pattern across the team | J61: Derived from the schedule in HCHB. | K61: Medium | L61: Assist | M61: Clinical Manager | N61: Weekly | O61: Live / computed | P61: — | Q61: Maybe | R61: N | S61: Medium | T61: Optimisable, but it touches human routines — assist rather than dictate. | U61: Nothing outstanding. | V61: Soft | W61: Assist | X61: System | Y61: In-system | Z61: Derived | AA61: Quantitative | AB61: Medium | AC61: SCH-N | AD61: 1 | AE61: N
A62: S-38 | B62: Scheduling Engine | C62: Engagement | D62: Exceptions | E62: Aligned | F62: Rebooking a visit that never happened | G62: Recovering a visit that was not worked. Spotting the miss is easy; choosing the new slot pulls in every soft constraint at once, which is why it is slow work today. | H62: Scheduler — rebooks | I62: Scheduler; DCS — when it will not resolve | J62: HCHB — visit status. The status the office sees can run hours behind because of the sync lag. | K62: Medium | L62: Assist | M62: Scheduler | N62: On event | O62: Live / computed | P62: — | Q62: Yes | R62: Y | S62: Low | T62: Sensing the miss is legible; the recovery pulls the whole problem back in. Note the visit states run scheduled, then documentation pending, then missed — so 'missed' is a late signal. | U62: Can we detect a likely miss earlier than the missed status appears? | V62: Hard | W62: Assist | X62: System | Y62: In-system | Z62: HCHB + Derived | AA62: Quantitative | AB62: Medium | AC62: SCH-M | AD62: 3 | AE62: N
A63: S-39 | B63: Scheduling Engine | D63: Exceptions | E63: Aligned | F63: Missed-visit documentation | G63: The compliance trail behind a missed visit — the note, and the physician notified within 48 hours. This is a Medicare requirement and a hard stop in the system, and it escalates if it is late. | H63: Clinician — documents; Scheduler — notifies the physician | I63: Scheduler; escalates to DCS if the 48 hours lapse | J63: HCHB — missed-visit workflow and notification record | K63: High | L63: Automate | M63: Scheduler; DCS on escalation | N63: On event | O63: Stable | P63: — | Q63: Yes | R63: N | S63: Low | T63: Workflow and compliance prompting — safe to automate, and already partly automated. | U63: Nothing outstanding. | V63: Config | W63: Control | X63: System | Y63: In-system | Z63: HCHB | AA63: Quantitative | AB63: High | AC63: SCH-M | AD63: 3 | AE63: N
A64: S-50 | B64: Scheduling Engine | C64: Engagement | D64: Exceptions | E64: Aligned | F64: The blind window before documentation syncs | G64: The gap between a visit happening and its documentation reaching the office. Today the office can only see that a visit was started or is incomplete — a visit performed Tuesday may not sync until Friday, and a started visit is not always one that happened. | H64: Clinician — syncs; the delay is nobody's task | I64: — no one measures it today | J64: HCHB, derived from the gap between visit time and sync time. | K64: Medium | L64: Surface | M64: Clinical Manager — owns the measure | N64: Continuous | O64: Live / computed | P64: — | Q64: Maybe | R64: N | S64: Low | T64: Added 19 Aug, and it constrains the whole design: nothing may depend on real-time visit state read out of HCHB. The workbook's example is stark — a clinician who called an ambulance has started a visit that did not happen, and the schedule still reads as worked. | U64: How long is the blind window in practice? Nobody has measured it.
A65: S-25 | B65: Engagement | C65: Engagement | D65: Matching | E65: Differs — the one-pager groups this under Scheduling Engine | F65: Times the patient will not accept | G65: A flat refusal of a time band — nothing before eleven, no afternoons. It removes slots outright and reshapes the whole route around it. | H65: Scheduler or Clinician — captures it in conversation | I65: Scheduler — schedules around it | J65: HCHB coordination note — free text written by a person, not a structured field. | K65: Medium | L65: Assist | M65: Scheduler | N65: Per episode, revisited in conversation | O65: Drifts — needs re-contact | P65: Day before — the confirmation round | Q65: Yes | R65: N | S65: Medium | T65: Hard once captured, but a stale refusal causes a failed visit — and in practice these soften with relationship. Worth re-testing rather than treating as permanent. | U65: Should refusals carry a review date so they do not calcify? | V65: Soft | W65: Assist | X65: Patient | Y65: Tacit | Z65: Manual | AA65: Qualitative | AB65: Medium | AC65: SCH-I | AD65: 3 | AE65: N
A66: S-26 | B66: Engagement | C66: Engagement | D66: Matching | E66: Differs — the one-pager groups this under Scheduling Engine | F66: Preferred visit window | G66: When the patient would like to be seen. Softer than a refusal, but it drives satisfaction and whether the visit actually happens. | H66: Scheduler or Clinician — captures it | I66: Scheduler — optimises toward it | J66: HCHB coordination note — free text. | K66: Medium | L66: Assist | M66: Scheduler | N66: Per episode | O66: Drifts — needs re-contact | P66: Day before — the confirmation round | Q66: Maybe | R66: N | S66: Low | T66: Optimise toward it, confirm before committing. | U66: Nothing outstanding. | V66: Soft | W66: Assist | X66: Patient | Y66: Tacit | Z66: Manual | AA66: Qualitative | AB66: Medium | AC66: SCH-I | AD66: 1 | AE66: N
A67: S-27 | B67: Engagement | D67: Matching | E67: Differs — the one-pager groups this under Scheduling Engine | F67: Days the patient is committed elsewhere | G67: Standing commitments that block whole days — dialysis on Monday, Wednesday and Friday, a regular clinic appointment. These are hard, and they are patient-reported. | H67: Scheduler or Clinician — captures it | I67: Scheduler — schedules around it | J67: HCHB coordination note — free text. | K67: Medium | L67: Assist | M67: Scheduler | N67: Per episode | O67: Drifts — needs re-contact | P67: Weekly — when the week is built | Q67: Yes | R67: Y | S67: Low | T67: A standing constraint, but patient-reported — trust and verify. | U67: Could standing commitments be captured as structured dates rather than free text? | V67: Hard | W67: Assist | X67: Patient | Y67: Tacit | Z67: Manual + HCHB | AA67: Qualitative | AB67: Medium | AC67: SCH-I | AD67: 3 | AE67: N
A68: S-28 | B68: Engagement | C68: Engagement | D68: Matching | E68: Differs — the one-pager groups this under Scheduling Engine | F68: Caregiver has to be present | G68: Some visits can only happen when a family member or carer is there — wound-care teaching, insulin, or simply to let the clinician in. It ties the visit to a second person's calendar. | H68: Scheduler or Clinician — confirms before booking | I68: Scheduler — and the Clinician on the day | J68: HCHB coordination note — free text. | K68: Medium | L68: Surface | M68: Scheduler — confirms with the family | N68: Per visit for affected patients | O68: Drifts — needs re-contact | P68: Day before — the confirmation round | Q68: Yes | R68: Y | S68: Medium | T68: The clearest 'surface, never decide' row on the sheet: a hard rule, a changing informal input, and a patient-safety consequence if it is wrong. | U68: How often does caregiver availability change mid-episode, and does anyone update the note when it does? | V68: Hard | W68: Read | X68: Caregiver | Y68: Tacit | Z68: Manual | AA68: Qualitative | AB68: Low | AC68: SCH-J | AD68: 3 | AE68: N
A69: S-29 | B69: Engagement | C69: Engagement | D69: Matching | E69: Differs — the one-pager groups this under Scheduling Engine | F69: Cognitive and dementia constraints | G69: When a patient cannot safely admit a clinician or follow instruction alone, a caregiver becomes a hard gate and the available windows narrow sharply. | H69: Clinician — identifies it; Scheduler — schedules to it | I69: Clinician — owns the clinical judgment | J69: Clinical detail in HCHB; the scheduling consequence in the coordination note. | K69: Medium | L69: Surface | M69: Clinician / Clinical Manager | N69: Per episode | O69: Drifts — needs re-contact | P69: At start of care | Q69: Yes | R69: Y | S69: Medium | T69: Cognition plus caregiver dependency plus safety. Automation must only surface. | U69: Nothing outstanding — but confirm the note reliably reaches the scheduler. | V69: Hard | W69: Read | X69: Caregiver | Y69: Tacit | Z69: Manual + HCHB | AA69: Qualitative | AB69: Low | AC69: SCH-J | AD69: 3 | AE69: N
A70: S-30 | B70: Engagement | C70: Engagement | D70: Matching | E70: Differs — the one-pager groups this under Scheduling Engine | F70: The caregiver's own changing schedule | G70: Scheduling around two moving calendars at once — the patient's and a carer who works rotating shifts. The hardest real case in the whole model, and almost entirely undocumented. | H70: Scheduler and Clinician — renegotiate as it changes | I70: Scheduler — with the family | J70: Not recorded anywhere in a durable form. | K70: Low | L70: Surface | M70: Scheduler | N70: Weekly, sometimes more | O70: Drifts — needs re-contact | P70: Day before — the confirmation round | Q70: Yes | R70: Y | S70: Medium | T70: Two undocumented moving calendars. A system can show what it last heard; it cannot know. | U70: Is there any value in capturing caregiver availability as structured data, or is it too volatile to be worth it? | V70: Hard | W70: Read | X70: Caregiver | Y70: Tacit | Z70: Manual | AA70: Qualitative | AB70: Low | AC70: SCH-J | AD70: 3 | AE70: N
A71: S-32 | B71: Engagement | C71: Engagement | D71: Matching | E71: Differs — the one-pager groups this under Scheduling Engine | F71: Competing medical appointments | G71: The patient's other appointments — dialysis, infusion, a specialist visit — that remove days or windows. Usually surfaces in conversation rather than in the record. | H71: Scheduler or Clinician — learns it by asking | I71: Scheduler | J71: HCHB coordination note when captured; otherwise not recorded. | K71: Medium | L71: Assist | M71: Scheduler | N71: Per episode, and it changes | O71: Drifts — needs re-contact | P71: Day before — the confirmation round | Q71: Yes | R71: Y | S71: Low | T71: Capturable if reported. The failure mode is a visit booked into an appointment nobody knew about. | U71: Nothing outstanding. | V71: Hard | W71: Assist | X71: Patient | Y71: Manual | Z71: Manual + HCHB | AA71: Quantitative | AB71: Medium | AC71: SCH-K | AD71: 3 | AE71: N
A72: S-23 | B72: Engagement | D72: Matching | E72: Differs — the one-pager groups this under Scheduling Engine | F72: Gender preference | G72: A patient's request for a clinician of a particular gender, often for cultural, religious or comfort reasons — and effectively hard when it applies to personal care. | H72: Scheduler — captures and matches | I72: Scheduler | J72: HCHB coordination note — free text. | K72: Medium | L72: Assist | M72: Scheduler | N72: Per episode | O72: Drifts — needs re-contact | P72: At start of care | Q72: No | R72: N | S72: Medium | T72: Sensitive. Surface and confirm rather than auto-matching on it. | U72: Is there a policy on how this is recorded and honoured? | V72: Hard/Soft | W72: Assist | X72: Patient | Y72: Tacit | Z72: Manual | AA72: Qualitative | AB72: Medium | AC72: SCH-H | AD72: 0 | AE72: N
A73: S-24 | B73: Engagement | C73: Engagement | D73: Matching | E73: Differs — the one-pager groups this under Scheduling Engine | F73: Language and cultural match | G73: Pairing a patient with a clinician who shares their language where possible. It materially affects teaching visits, where the whole point is that the patient understands. | H73: Scheduler — matches where they can | I73: Scheduler; Clinician — raises it when teaching fails | J73: Languages spoken are not reliably recorded for clinicians; patient language is in HCHB. | K73: Low | L73: Assist | M73: Scheduler | N73: Per episode | O73: Drifts — needs re-contact | P73: At start of care | Q73: Maybe | R73: N | S73: Low | T73: Capturable on both sides, and worth confirming specifically for teaching-critical visits. | U73: Do we hold clinician language capability anywhere today? | V73: Soft | W73: Assist | X73: Patient | Y73: Tacit | Z73: Manual | AA73: Qualitative | AB73: Medium | AC73: SCH-H | AD73: 1 | AE73: N
A74: CO-04 | B74: Engagement | D74: Before the visit | E74: Aligned | F74: New-patient welcome call | G74: The first call to a newly referred patient. Today it carries a real judgment as well as a greeting: is the patient actually home, or still in hospital, or putting admission off? It happens before anyone is sent out, which is precisely why nobody is sent to an empty house. | H74: Scheduler — makes the call | I74: Scheduler — makes the one true judgment call in the current process | J74: HCHB — the visit and the coordination note that follows. | K74: Medium | L74: Assist | M74: Scheduler | N74: Per referral | O74: This is the contact | P74: — | Q74: Maybe | R74: N | S74: Medium | T74: Automate the trigger and the routine parts; keep a person on the line for the judgment. This is the highest-value human call in the admission chain. | U74: If outreach is automated, how do we preserve the 'is the patient really home' check? | V74: Soft | W74: Assist | X74: System | Y74: In-system | Z74: Telephony + HCHB | AA74: Quantitative | AB74: Medium | AC74: CRD-A | AD74: 1 | AE74: N
A75: CO-06 | B75: Engagement | C75: Scheduling | D75: Before the visit | E75: Aligned | F75: Confirming availability before booking | G75: Checking the patient — and where needed the caregiver — can actually make a slot before it is committed. It prevents booking into a window that was always going to fail. | H75: Scheduler — confirms | I75: Scheduler | J75: Not systematically recorded; the confirmation happens in conversation. | K75: Low | L75: Surface | M75: Scheduler | N75: Per visit at booking | O75: This is the contact | P75: — | Q75: Yes | R75: Y | S75: Medium | T75: Feeds directly off the caregiver-availability rows, which are the least reliable data on the sheet. Surface what is known; do not presume it is current. | U75: Nothing outstanding — but this row depends on S-28 and S-30 being right. | V75: Hard | W75: Read | X75: Patient | Y75: Tacit | Z75: Manual | AA75: Qualitative | AB75: Low | AC75: CRD-B | AD75: 3 | AE75: N
A76: CO-01 | B76: Engagement | C76: Capacity | D76: Before the visit | E76: Aligned | F76: Day-before confirmation | G76: The call that confirms tomorrow's visit will actually happen. It is the single biggest reducer of failed visits — and today every clinician does it by hand, for every patient, every day. The system sends nothing. | H76: Clinician — calls or texts each patient the evening before | I76: Clinician — and picks the disposition straight afterwards | J76: The call is not recorded. Its outcome shows up as the disposition selected in HCHB. | K76: High | L76: Automate | M76: Clinician — takes over when the automated round surfaces a problem | N76: Daily, day before | O76: This is the contact | P76: — | Q76: Yes | R76: N | S76: High | T76: The largest single block of clinician time this initiative can hand back. The one-pager now commits to automating the round and to keeping the schedule pliable until confirmation, so changes can land before the patient is told. The care in the design is that the call also surfaces things a reminder never would. | U76: How do we automate the round without losing what the conversation catches? | V76: Soft | W76: Assist | X76: Clinician | Y76: Manual | Z76: Manual | AA76: Quantitative | AB76: Medium | AC76: CRD-A | AD76: 3 | AE76: N
A77: CO-02 | B77: Engagement | D77: Before the visit | E77: Aligned | F77: Automated reminders | G77: System-sent reminders ahead of a visit. A clean, low-risk automation that reduces no-shows without consuming anyone's time — and one Homecare Homebase does not do today. | H77: — nobody; this does not happen today | I77: — no one today; this does not happen | J77: Does not exist today. Would need an outbound channel. | K77: High | L77: Automate | M77: — exception only | N77: Per visit | O77: This is the contact | P77: — | Q77: Yes | R77: Y | S77: Low | T77: Deterministic and safe. This is the most obvious quick win in the engagement arena. | U77: Nothing outstanding. | V77: Soft | W77: Control | X77: System | Y77: In-system | Z77: Telephony | AA77: Quantitative | AB77: High | AC77: CRD-A | AD77: 3 | AE77: Y
A78: CO-03 | B78: Engagement | D78: Before the visit | E78: Aligned | F78: On-my-way notification | G78: Telling the patient the clinician is roughly twenty minutes out. It is fully derivable from the live route and it materially changes the experience of waiting. | H78: — nobody; this does not happen today | I78: — no one today; this does not happen | J78: Does not exist today. Would derive from route and position. | K78: High | L78: Automate | M78: — exception only | N78: Per visit | O78: This is the contact | P78: — | Q78: Maybe | R78: N | S78: Medium | T78: Deterministic from position and route. Note it implies clinician location tracking, which is a conversation to have deliberately. | U78: Are we comfortable with the location tracking this implies, and have clinicians been consulted? | V78: Soft | W78: Control | X78: Clinician | Y78: In-system | Z78: Routing | AA78: Quantitative | AB78: High | AC78: CRD-A | AD78: 1 | AE78: N
A79: CO-05 | B79: Engagement | D79: Before the visit | E79: Aligned | F79: Channel and communication preferences | G79: How each patient wants to be reached — text, call or email — and what they have consented to. It decides whether any of the automation above actually lands. | H79: Scheduler — captures it when it comes up | I79: Scheduler | J79: Phone numbers are in HCHB. Channel preference and consent are not systematically held. | K79: Low | L79: Assist | M79: Scheduler | N79: Per episode | O79: Drifts — needs re-contact | P79: At start of care | Q79: Maybe | R79: N | S79: Low | T79: Honour it, never assume it. Conflict risk: a vendor with its own communication model may not respect an existing preference store. Consent and opt-out rules also carry regulatory weight. | U79: Where would channel preference and consent live, and who captures it at admission? | V79: Soft | W79: Assist | X79: System | Y79: Manual | Z79: Manual + Config | AA79: Quantitative | AB79: Medium | AC79: CRD-A | AD79: 1 | AE79: Y
A80: S-47 | B80: Engagement | C80: Scheduling | D80: Before the visit | E80: Aligned | F80: Power of attorney and who can sign | G80: Whether someone other than the patient holds legal authority to sign admission consents and to be the contact of record. Where a power of attorney exists the patient's own agreement does not satisfy consent, and some direct that the patient not be contacted at all. | H80: Intake and Scheduler — capture it if it surfaces | I80: Scheduler — decides who to contact | J80: Partly Commure at referral, otherwise manual. Not reliably known before the visit is booked. | K80: Low | L80: Assist | M80: Scheduler — confirms who may be contacted | N80: Per referral, before booking | O80: Drifts — needs re-contact | P80: At referral / welcome call | Q80: Yes | R80: Y | S80: Medium | T80: Added 19 Aug. The failure it prevents is concrete: a nurse arrives for the start of care, the patient cannot sign, and the power of attorney is two states away. The visit is wasted and the clock keeps running. | U80: Where would POA status be captured so the scheduler sees it before booking rather than after?
A81: CO-13 | B81: Engagement | D81: Before the visit | E81: Aligned | F81: A verified number for the right person | G81: The confirmed phone number and reachable channel for the patient and, where it applies, the caregiver or power of attorney — including which of them is the right person to talk to about scheduling. Every piece of coordination depends on this, and today it is scattered. | H81: Intake and Scheduler — capture what they are given | I81: Scheduler — works out who to call | J81: Partly HCHB, partly Commure, partly neither. There is no single verified record. | K81: Low | L81: Automate | M81: Scheduler — owns the exception when nobody answers | N81: Per referral, verified at admission | O81: Drifts — needs re-contact | P81: At referral / welcome call | Q81: Yes | R81: Y | S81: Low | T81: Added 19 Aug, and distinct from channel preference: a preference is no use without a working number for the right party. The failure it names is reminders going to a disconnected mobile while the daughter who books every visit is never contacted. | U81: Who verifies the number, and at what point in admission?
A82: CO-14 | B82: Engagement | D82: Before the visit | E82: Aligned | F82: Consent to contact, by channel | G82: Which channels we are legally allowed to use — texting, and sharing information with family — and whether the consent has actually been signed. A legal gate rather than a preference. | H82: Clinician — obtains consent at the start-of-care visit | I82: — enforced by rule, not decided by anyone | J82: HCHB, once signed at admission. | K82: Medium | L82: Automate | M82: — exception only | N82: Per episode, signed at the start of care | O82: Stable | P82: — | Q82: Yes | R82: Y | S82: Low | T82: Added 19 Aug, and it puts a hard boundary on the automation the one-pager promises: consents are signed at the start-of-care visit, so no automated texting can precede admission and the readiness call before that first visit is necessarily a voice call. | U82: Does this change what we can promise vendors about pre-admission outreach?
A83: CO-07 | B83: Engagement | C83: Scheduling | D83: When plans change | E83: Aligned | F83: Rescheduling with the patient | G83: Negotiating a new time when the planned one stops working. A system can propose slots; the negotiation itself is a conversation between people. | H83: Clinician — for their own visits; Scheduler — when it comes back to the office | I83: Clinician or Scheduler, depending on who holds it | J83: The outcome lands in HCHB as a rescheduled visit; the negotiation is not recorded. | K83: Medium | L83: Surface | M83: Clinician / Scheduler | N83: On event | O83: This is the contact | P83: — | Q83: Maybe | R83: N | S83: Medium | T83: Human negotiation around a moving constraint. Note that when rapid reschedule is switched on, a clinician moving their own visit inside the week creates no office work at all — so the volume the office sees is a branch configuration choice, not a fact. | U83: Which branches have rapid reschedule enabled? It changes what the office actually sees. | V83: Soft | W83: Read | X83: Clinician | Y83: Tacit | Z83: Manual | AA83: Qualitative | AB83: Low | AC83: CRD-B | AD83: 1 | AE83: N
A84: CO-08 | B84: Engagement | C84: Scheduling | D84: When plans change | E84: Aligned | F84: Following up a failed or no-show visit | G84: Chasing the visit that did not happen — reaching the patient, rebooking, documenting. Left alone these become both a compliance problem and lost revenue. | H84: Scheduler — follows up and rebooks | I84: Scheduler; DCS — when it will not resolve | J84: HCHB — visit status and missed-visit workflow. | K84: Medium | L84: Assist | M84: Scheduler | N84: On event | O84: This is the contact | P84: — | Q84: Yes | R84: Y | S84: Low | T84: Detection is clean; the recovery pulls in every soft constraint again. | U84: Nothing outstanding. | V84: Hard | W84: Assist | X84: Branch | Y84: Manual | Z84: HCHB + Manual | AA84: Qualitative | AB84: Medium | AC84: CRD-B | AD84: 3 | AE84: N
A85: CO-09 | B85: Engagement | C85: Capacity, Scheduling | D85: When plans change | E85: Ruled 25 Aug — moved to Engagement. The 8.19 workbook still has it under Scheduling Engine; write this back to the workbook | F85: Finding coverage when someone calls out | G85: The scramble when a clinician is out. It is owned jointly by the DCS and the scheduler, and it runs on who will actually say yes — calls, texts and Teams messages to full-time and per-diem staff, then reassignment or moving the visit to another day. | H85: DCS and Scheduler — jointly | I85: DCS and Scheduler — jointly; DCS escalates for a start of care | J85: No system holds this. It runs on phone, text and Teams, against the scheduler's knowledge of who might take it. | K85: Low | L85: Surface | M85: DCS and Scheduler — jointly | N85: On event | O85: This is the contact | P85: — | Q85: Yes | R85: Y | S85: High | T85: Runs on the same relational willingness as the per-diem and elasticity rows. A system can assemble the candidate list and reach people directly; it cannot decide who will say yes. This is where an incentive on a hard-to-fill visit would attach. | U85: Would we let the system contact clinicians directly with an open visit, or must a person always make the ask? | V85: Hard | W85: Read | X85: Branch | Y85: Tacit | Z85: Manual | AA85: Qualitative | AB85: Low | AC85: CRD-B | AD85: 3 | AE85: N
A86: CO-15 | B86: Engagement | C86: Capacity | D86: Incentives & offers | E86: Aligned | F86: Incentives and offers on hard-to-fill visits | G86: Surfacing a difficult visit to the clinicians who could take it, with whatever incentive or differential is attached. The one-pager now asks vendors about this and the questionnaire scores it — but no variable in the inventory covers it. | H86: — does not exist today | I86: — no one today; does not exist | J86: Nothing today. Pay model is in Workday; there is no mechanism for a visit-level offer. | K86: High | L86: Assist | M86: Branch Leadership (ED) — would own the spend | N86: On event | O86: Drifts — needs re-contact | P86: On event — coverage and surge | Q86: -- | R86: N | S86: High | T86: A genuine gap, not an oversight: this was added to the vendor ask on 21 Aug and the 19 Aug inventory predates it. Recorded here so the workbook and the questionnaire stay aligned. Next free IDs after 19 Aug are SH-10, C-15, S-51 and CO-15. | U86: Numbered 27 Aug. Confirm MVP and gating — it is asked of vendors in Part B row 10.
A87: CO-10 | B87: Engagement | C87: Scheduling | D87: Across the care team | E87: Ruled 25 Aug — moved to Engagement. The 8.19 workbook still has it under Scheduling Engine; write this back to the workbook | F87: Coordinating visits across disciplines | G87: Spacing the nurse, the therapist and the aide sensibly across a week rather than stacking two on one day and leaving the patient idle the next. | H87: Scheduler — spaces them; Clinician — adjusts | I87: Scheduler | J87: HCHB holds the visits; the spacing judgment is manual. | K87: Medium | L87: Assist | M87: Scheduler | N87: Weekly per patient | O87: This is the contact | P87: — | Q87: Maybe | R87: N | S87: Low | T87: Rule-informed but bounded by what a patient will tolerate in a week. Propose, do not dictate. | U87: Is there a standard on how many visits a patient should have in one day? | V87: Soft | W87: Assist | X87: System | Y87: Manual | Z87: HCHB + Manual | AA87: Qualitative | AB87: Medium | AC87: CRD-C | AD87: 1 | AE87: N
A88: CO-11 | B88: Engagement | C88: Scheduling | D88: Across the care team | E88: Ruled 25 Aug — moved to Engagement. The 8.19 workbook still has it under Scheduling Engine; write this back to the workbook | F88: Keeping the team and the office in step | G88: The connective work of telling the case manager and the office when something changes. Today it is the coordination-note habit — and how well it works depends entirely on people remembering. | H88: Scheduler and Clinician — write the notes | I88: Case Manager / Clinical Manager — act on what they read | J88: HCHB coordination notes. | K88: Medium | L88: Assist | M88: Clinical Manager | N88: Continuous | O88: This is the contact | P88: — | Q88: Maybe | R88: N | S88: Low | T88: Logging and notifying is automatable; deciding what deserves an escalation is human judgment. | U88: Nothing outstanding. | V88: Soft | W88: Assist | X88: System | Y88: In-system | Z88: HCHB | AA88: Qualitative | AB88: Medium | AC88: CRD-C | AD88: 1 | AE88: N
A89: CO-12 | B89: Engagement | C89: Capacity, Scheduling | D89: Across the care team | E89: Ruled 25 Aug — moved to Engagement. The 8.19 workbook still has it under Scheduling Engine; write this back to the workbook | F89: What coordination actually costs | G89: The time clinicians and schedulers spend on coordination rather than care. It is capacity, and today it is invisible — roughly forty-five minutes a day per clinician by one estimate, which is a visit. | H89: Everyone — it is spread across every role | I89: — no one measures it today | J89: Not measured anywhere. | K89: Low | L89: Surface | M89: Clinical Manager / Branch Leadership — to act on the trend | N89: Continuous | O89: Live / computed | P89: — | Q89: Maybe | R89: N | S89: Low | T89: Measure and surface it; do not try to control the people doing it. This is the number that turns the business case from theory into a figure the branch recognises. | U89: Is there an appetite to measure this directly, or should it be estimated from the automation we remove? | V89: Derived | W89: Read | X89: Branch | Y89: Tacit | Z89: Derived + Manual | AA89: Quantitative | AB89: Low | AC89: CRD-D | AD89: 1 | AE89: N
A90: S-51 | B90: Scheduling Engine | C90: Engagement | D90: Exceptions | E90: Aligned | F90: The clinician's five dispositions | G90: What the clinician does with a visit the day before: accept it, reschedule it inside the week, reassign it, decline it, or mark it a missed visit. All are selections in HCHB. Reassign hands the visit back to the scheduler with a recommendation attached; decline hands it back without one and the branch places it elsewhere. The reason behind the choice is not captured anywhere. | H90: Clinician | I90: Scheduler | J90: HCHB — the disposition is recorded; the reason is not | K90: High | L90: Assist | M90: Scheduler | N90: Day before the visit | O90: Drifts — needs re-contact | P90: Day before — the confirmation round | Q90: -- | T90: The reassign recommendation is the clinician already doing the tool's job by hand, which makes it the best training signal in the whole process. Today it is typed into a note and lost. | U90: Confirm MVP, gating and posture. Do we capture a structured reason code, and is that a hard ask of the vendor or a phase-two ambition?
A91: S-52 | B91: Scheduling Engine | C91: Capacity Management | D91: Routing & the week | E91: Aligned | F91: The clinician's own weekly plan | G91: In steady state the clinician plots their own week — which patients on which days, in what order, around their own commitments. Nobody has written down how that decision is made. | H91: Clinician | I91: — no one today | J91: Nowhere — it lives in the clinician's head and their own notes | K91: Medium | L91: Assist | M91: Clinician | N91: Weekly | O91: Drifts — needs re-contact | P91: Weekly — when the week is built | Q91: -- | T91: The largest undocumented decision process in the model, and the one any tool most risks overriding. Automating around it without understanding it is how these deployments fail. | U91: Confirm MVP, gating and posture. This needs a scheduler and clinician session before it can be specified properly.
A92: S-53 | B92: Scheduling Engine | D92: Availability & reach | E92: Aligned | F92: Physical barriers and crossing windows | G92: Geography that distance alone does not capture: one zip split by a bridge into two sides that are not interchangeable, or an interstate crossing that is only passable in certain windows. | H92: Scheduler | I92: Scheduler | J92: Nowhere formally — it is local knowledge held by the scheduler | K92: Medium | L92: Automate | M92: Scheduler | N92: Slow-changing | O92: Stable | P92: Not re-checked today | Q92: -- | T92: Cheap to model once the routing data source is settled, and invisible until a clinician is sent somewhere they cannot reasonably get to. | U92: Is this a territory attribute or a routing penalty? The placement decides the layer. Also depends on the drive-time data source decision still open on S-17.
A93: S-54 | B93: Scheduling Engine | D93: Matching | E93: Aligned | F93: Hand-off to one's own assistant | G93: Whether a nurse can pass a visit directly to the LPN she supervises, and whether she can see that assistant's schedule at all. HCHB blocks both today. | H93: Clinician | I93: Scheduler | J93: HCHB — blocked by the permission model | K93: High | L93: Surface | M93: Clinical Manager | N93: Per visit | O93: Stable | P93: Not re-checked today | Q93: -- | T93: Both restrictions are HCHB design choices, not Medicare rules — which means they are negotiable, and worth naming to a vendor as something we would want to work differently. | U93: Confirm MVP, gating and posture. Pairs with S-51 — the accept/decline loop is where a hand-off would actually happen.
A94: CO-16 | B94: Engagement | C94: Scheduling Engine | D94: Incentives & offers | E94: Aligned | F94: A self-serve board of open visits | G94: Somewhere a clinician can see visits that need covering and take one, rather than waiting to be called. HCHB's Shift Finder does this and is not switched on. | H94: — no one today | I94: — no one today | J94: HCHB Shift Finder exists but is not enabled | K94: High | L94: Assist | M94: Branch Leadership (ED) | N94: On event | O94: Live / computed | P94: On event — coverage and surge | Q94: -- | T94: Pairs directly with CO-15: a board is where an incentive would be displayed. NVA coding already pays differentiated rates, so the pay mechanism partly exists. | U94: Confirm MVP, gating and posture. This is an incentive-policy decision as much as a product one, and it overlaps CO-15 — decide whether they are one row or two.

Sheet Lists
A1: Arena (8.19 workbook) | B1: Confidence | C1: Future state -- the tool's role | D1: Adoption sensitivity | E1: MVP | F1: Gating | G1: Trigger / how often | H1: Roles (for the two owner columns) | I1: Stays true on its own? | J1: Re-checked when
A2: Capacity Management | B2: High | C2: Automate | D2: High | E2: Yes | F2: Y | G2: Per referral | H2: Intake | I2: Stable | J2: At referral / welcome call
A3: Scheduling Engine | B3: Medium | C3: Assist | D3: Medium | E3: Maybe | F3: N | G3: Per episode | H3: Auth team | I3: Drifts — needs re-contact | J3: At start of care
A4: Engagement | B4: Low | C4: Surface | D4: Low | E4: No | G4: Per visit | H4: Scheduler | I4: Live / computed | J4: Weekly — when the week is built
C5: Stays manual | E5: -- | G5: Daily | H5: DCS | I5: This is the contact | J5: Day before — the confirmation round
G6: Day before the visit | H6: Clinician | J6: At recertification
G7: Weekly | H7: Clinical Manager | J7: On event — coverage and surge
G8: Quarterly | H8: Branch Leadership (ED) | J8: Not re-checked today
G9: On event | H9: Per Diem / Float | J9: —
G10: Continuous | H10: Case Manager
G11: Config | H11: HR / Talent
G12: Slow-changing | H12: Corporate / Operations
G13: One-time decision | H13: Patient / Caregiver
H14: -- no one today

Sheet Roles
B1: Roles, and the colours they carry on the current-state flow maps
B2: Use these names in the two owner columns. Keeping the vocabulary identical is what lets the future-state maps be drawn straight from this workbook.
B4: Role | C4: Colour | D4: What they do | E4: When they appear
B5: Intake | C5: #1F6F78 | D5: Receives the referral in Commure, and gives the final approval that releases it for scheduling. | E5: Admission
B6: Auth team | C6: #DF751D | D6: Verifies eligibility and keys the pending authorisation. Writes the payer's rules into a coordination note at verification — days before the plan of care is written. | E6: Admission, and every add-on, recert and resumption
B7: Scheduler (PCC) | C7: #C6A01F | D7: Makes the welcome call, books the start of care and evals, assigns every visit the frequency generates in one pass, and works the exception queues. Largely an administrator — the welcome call is the one real judgment call. | E7: Throughout
B8: DCS | C8: #792E2E | D8: Reviews the referral, approves the plan of care, owns add-on workflow, and shares call-out coverage with the scheduler. Escalation point for missed compliance. | E8: Throughout
B9: Clinician | C9: #2E599D | D9: Performs the visits, plots their own discipline's frequency, builds and confirms their own week after the plan of care, and selects the disposition the day before. | E9: Throughout
B10: Clinical Manager | C10: #2E599D | D10: Manages individuals against productivity, competency and ramp. The role that reads most of the reports on this sheet. | E10: Weekly and monthly
B11: Branch Leadership (ED) | C11: #1A1A1A | D11: One home in the current-state maps: the joint review pulled when capacity tightens — territory alignment and referral acceptance. | E11: When capacity tightens
B12: Per Diem / Float | C12: #795933 | D12: No territory, on purpose. A targeted instrument — take the admissions, or take coverage visits to free a territory clinician. | E12: On event
B13: HCHB | C13: #795CA7 | D13: The system acting by itself: generating tasks, applying rules, checking authorisation, suggesting a route. A workflow in HCHB worked by a person carries that person's colour, not this one. | E13: Continuous
